christianwhocodes/__init__.py
christianwhocodes/cli.py
christianwhocodes/generators/__init__.py
christianwhocodes/generators/file.py
christianwhocodes/py.typed
christianwhocodes/utils/__init__.py
christianwhocodes/utils/enums.py
christianwhocodes/utils/helpers.py
christianwhocodes/utils/platform.py
christianwhocodes/utils/pyproject.py
christianwhocodes/utils/stdout.py
christianwhocodes/utils/types.py
christianwhocodes/utils/urls.py
christianwhocodes/utils/version.py
christianwhocodes-1.2.6.dist-info/WHEEL
christianwhocodes-1.2.6.dist-info/entry_points.txt
christianwhocodes-1.2.6.dist-info/METADATA
christianwhocodes-1.2.6.dist-info/RECORD
