Metadata-Version: 2.3
Name: christianwhocodes
Version: 1.2.6
Summary: Python code utilities for developers.
Author: Kevin Wakhisi
Author-email: Kevin Wakhisi <kevin@christianwhocodes.space>
License: MIT License
Requires-Dist: pyperclip>=1.11.0
Requires-Dist: rich>=14.2.0
Requires-Python: >=3.12
Project-URL: homepage, https://github.com/christianwhocodes/pkg-christianwhocodes#readme
Project-URL: repository, https://github.com/christianwhocodes/pkg-christianwhocodes
Project-URL: issues, https://github.com/christianwhocodes/pkg-christianwhocodes/issues
